<?xml version="1.0" encoding="utf-8" ?><dwsync><file name="_alert.scss" server="www.blackaeonium.net" local="3797295352" remote="3797156640" Dst="-1" /><file name="_backdrop.scss" server="www.blackaeonium.net" local="3797295353" remote="3797156640" Dst="-1" /><file name="_banner.scss" server="www.blackaeonium.net" local="3797295353" remote="3797156640" Dst="-1" /><file name="_border-radius.scss" server="www.blackaeonium.net" local="3797295353" remote="3797156640" Dst="-1" /><file name="_box-shadow.scss" server="www.blackaeonium.net" local="3797295354" remote="3797156640" Dst="-1" /><file name="_breakpoints.scss" server="www.blackaeonium.net" local="3797295355" remote="3797156640" Dst="-1" /><file name="_buttons.scss" server="www.blackaeonium.net" local="3797295355" remote="3797156640" Dst="-1" /><file name="_caret.scss" server="www.blackaeonium.net" local="3797295356" remote="3797156640" Dst="-1" /><file name="_clearfix.scss" server="www.blackaeonium.net" local="3797295356" remote="3797156640" Dst="-1" /><file name="_color-mode.scss" server="www.blackaeonium.net" local="3797295356" remote="3797156640" Dst="-1" /><file name="_color-scheme.scss" server="www.blackaeonium.net" local="3797295357" remote="3797156640" Dst="-1" /><file name="_container.scss" server="www.blackaeonium.net" local="3797295358" remote="3797156640" Dst="-1" /><file name="_deprecate.scss" server="www.blackaeonium.net" local="3797295358" remote="3797156640" Dst="-1" /><file name="_forms.scss" server="www.blackaeonium.net" local="3797295359" remote="3797156640" Dst="-1" /><file name="_gradients.scss" server="www.blackaeonium.net" local="3797295359" remote="3797156640" Dst="-1" /><file name="_grid.scss" server="www.blackaeonium.net" local="3797295359" remote="3797156640" Dst="-1" /><file name="_image.scss" server="www.blackaeonium.net" local="3797295360" remote="3797156640" Dst="-1" /><file name="_list-group.scss" server="www.blackaeonium.net" local="3797295361" remote="3797156640" Dst="-1" /><file name="_lists.scss" server="www.blackaeonium.net" local="3797295361" remote="3797156640" Dst="-1" /><file name="_pagination.scss" server="www.blackaeonium.net" local="3797295362" remote="3797156640" Dst="-1" /><file name="_reset-text.scss" server="www.blackaeonium.net" local="3797295362" remote="3797156640" Dst="-1" /><file name="_resize.scss" server="www.blackaeonium.net" local="3797295362" remote="3797156640" Dst="-1" /><file name="_table-variants.scss" server="www.blackaeonium.net" local="3797295363" remote="3797156640" Dst="-1" /><file name="_text-truncate.scss" server="www.blackaeonium.net" local="3797295364" remote="3797156640" Dst="-1" /><file name="_transition.scss" server="www.blackaeonium.net" local="3797295364" remote="3797156640" Dst="-1" /><file name="_visually-hidden.scss" server="www.blackaeonium.net" local="3797295365" remote="3797156640" Dst="-1" /><file name="_utilities.scss" server="www.blackaeonium.net" local="3797295365" remote="3797156640" Dst="-1" /></dwsync>